transport_co2/__init__.py
transport_co2/__version__.py
transport_co2/estimator.py
transport_co2/model.py
transport_co2-0.3.0.dist-info/METADATA
transport_co2-0.3.0.dist-info/WHEEL
transport_co2-0.3.0.dist-info/top_level.txt
transport_co2-0.3.0.dist-info/RECORD
