Metadata-Version: 2.1
Name: transport-co2
Version: 0.3.0
Summary: Calculate CO2 emissions for personal mobility.
Home-page: https://github.com/maasglobal/sustainable-mobility-api
Author: Brylie Christopher Oxley, Markus Schepke
Author-email: brylie.oxley@maas.global, markus.schepke@maas.global
License: MIT
Project-URL: Documentation, https://github.com/maasglobal/sustainable-mobility-api/tree/master/estimator/README.md
Project-URL: Source, https://github.com/maasglobal/sustainable-mobility-api/tree/master/estimator
Project-URL: Tracker, https://github.com/maasglobal/sustainable-mobility-api/issues
Keywords: transport,co2,carbon,sustainability,mobility
Platform: UNKNOWN
Classifier: License :: OSI Approved :: MIT License
Classifier: Programming Language :: Python
Classifier: Programming Language :: Python :: 3
Classifier: Programming Language :: Python :: 3.6
Classifier: Programming Language :: Python :: 3.7
Classifier: Programming Language :: Python :: 3.8
Classifier: Development Status :: 5 - Production/Stable
Classifier: Intended Audience :: Developers
Classifier: Intended Audience :: Education
Classifier: Intended Audience :: Science/Research
Classifier: Natural Language :: English
Classifier: Topic :: Scientific/Engineering :: GIS
Classifier: Typing :: Typed
Requires-Python: >=3.6.0
